
{
  "header": {
    "reportVersion": 1,
    "event": "Allocation failed - JavaScript heap out of memory",
    "trigger": "FatalError",
    "filename": "report.20200901.133607.12380.0.001.json",
    "dumpEventTime": "2020-09-01T13:36:07Z",
    "dumpEventTimeStamp": "1598978167728",
    "processId": 12380,
    "cwd": "C:\\EmerixEAG",
    "commandLine": [
      "C:\\Program Files\\nodejs\\node.exe",
      "C:\\EmerixEAG\\node_modules\\@ngtools\\webpack\\src\\type_checker_worker.js",
      "9d93e901-158a-4cf9-ba1b-2f0582ffcfeb"
    ],
    "nodejsVersion": "v12.15.0",
    "wordSize": 64,
    "arch": "x64",
    "platform": "win32",
    "componentVersions": {
      "node": "12.15.0",
      "v8": "7.7.299.13-node.16",
      "uv": "1.33.1",
      "zlib": "1.2.11",
      "brotli": "1.0.7",
      "ares": "1.15.0",
      "modules": "72",
      "nghttp2": "1.40.0",
      "napi": "5",
      "llhttp": "2.0.4",
      "http_parser": "2.9.3",
      "openssl": "1.1.1d",
      "cldr": "35.1",
      "icu": "64.2",
      "tz": "2019c",
      "unicode": "12.1"
    },
    "release": {
      "name": "node",
      "lts": "Erbium",
      "headersUrl": "https://nodejs.org/download/release/v12.15.0/node-v12.15.0-headers.tar.gz",
      "sourceUrl": "https://nodejs.org/download/release/v12.15.0/node-v12.15.0.tar.gz",
      "libUrl": "https://nodejs.org/download/release/v12.15.0/win-x64/node.lib"
    },
    "osName": "Windows_NT",
    "osRelease": "10.0.18363",
    "osVersion": "Windows 10 Enterprise",
    "osMachine": "x86_64",
    "cpus": [
      {
        "model": "Intel(R) Core(TM) i7-8700 CPU @ 3.20GHz",
        "speed": 3192,
        "user": 137305031,
        "nice": 0,
        "sys": 86745796,
        "idle": 4062518703,
        "irq": 2527078
      },
      {
        "model": "Intel(R) Core(TM) i7-8700 CPU @ 3.20GHz",
        "speed": 3192,
        "user": 28264156,
        "nice": 0,
        "sys": 26845125,
        "idle": 4231460250,
        "irq": 1235203
      },
      {
        "model": "Intel(R) Core(TM) i7-8700 CPU @ 3.20GHz",
        "speed": 3192,
        "user": 150367718,
        "nice": 0,
        "sys": 56641625,
        "idle": 4079560187,
        "irq": 1704062
      },
      {
        "model": "Intel(R) Core(TM) i7-8700 CPU @ 3.20GHz",
        "speed": 3192,
        "user": 30946765,
        "nice": 0,
        "sys": 17712078,
        "idle": 4237910687,
        "irq": 1199765
      },
      {
        "model": "Intel(R) Core(TM) i7-8700 CPU @ 3.20GHz",
        "speed": 3192,
        "user": 60674359,
        "nice": 0,
        "sys": 36617859,
        "idle": 4189277171,
        "irq": 1549843
      },
      {
        "model": "Intel(R) Core(TM) i7-8700 CPU @ 3.20GHz",
        "speed": 3192,
        "user": 30784000,
        "nice": 0,
        "sys": 19016343,
        "idle": 4236769046,
        "irq": 1241281
      },
      {
        "model": "Intel(R) Core(TM) i7-8700 CPU @ 3.20GHz",
        "speed": 3192,
        "user": 63854312,
        "nice": 0,
        "sys": 33255750,
        "idle": 4189459328,
        "irq": 1756750
      },
      {
        "model": "Intel(R) Core(TM) i7-8700 CPU @ 3.20GHz",
        "speed": 3192,
        "user": 29895531,
        "nice": 0,
        "sys": 19035406,
        "idle": 4237638453,
        "irq": 1066703
      },
      {
        "model": "Intel(R) Core(TM) i7-8700 CPU @ 3.20GHz",
        "speed": 3192,
        "user": 32978390,
        "nice": 0,
        "sys": 16635812,
        "idle": 4236955187,
        "irq": 291140
      },
      {
        "model": "Intel(R) Core(TM) i7-8700 CPU @ 3.20GHz",
        "speed": 3192,
        "user": 16643250,
        "nice": 0,
        "sys": 9727218,
        "idle": 4260198921,
        "irq": 117437
      },
      {
        "model": "Intel(R) Core(TM) i7-8700 CPU @ 3.20GHz",
        "speed": 3192,
        "user": 24825062,
        "nice": 0,
        "sys": 18799906,
        "idle": 4242944421,
        "irq": 355328
      },
      {
        "model": "Intel(R) Core(TM) i7-8700 CPU @ 3.20GHz",
        "speed": 3192,
        "user": 26849125,
        "nice": 0,
        "sys": 14055593,
        "idle": 4245664671,
        "irq": 215671
      }
    ],
    "networkInterfaces": [
      {
        "name": "Ethernet",
        "internal": false,
        "mac": "b4:2e:99:61:80:c7",
        "address": "192.168.2.19",
        "netmask": "255.255.255.0",
        "family": "IPv4"
      },
      {
        "name": "Ethernet 3",
        "internal": false,
        "mac": "0a:00:27:00:00:10",
        "address": "192.168.56.1",
        "netmask": "255.255.255.0",
        "family": "IPv4"
      },
      {
        "name": "Loopback Pseudo-Interface 1",
        "internal": true,
        "mac": "00:00:00:00:00:00",
        "address": "::1",
        "netmask": "ffff:ffff:ffff:ffff:ffff:ffff:ffff:ffff",
        "family": "IPv6",
        "scopeid": 0
      },
      {
        "name": "Loopback Pseudo-Interface 1",
        "internal": true,
        "mac": "00:00:00:00:00:00",
        "address": "127.0.0.1",
        "netmask": "255.0.0.0",
        "family": "IPv4"
      },
      {
        "name": "vEthernet (Default Switch)",
        "internal": false,
        "mac": "00:15:5d:dc:13:45",
        "address": "192.168.125.209",
        "netmask": "255.255.255.240",
        "family": "IPv4"
      }
    ],
    "host": "WKS143"
  },
  "javascriptStack": {
    "message": "No stack.",
    "stack": [
      "Unavailable."
    ]
  },
  "nativeStack": [
    {
      "pc": "0x00007ff7c4531759",
      "symbol": "std::basic_ostream<char,std::char_traits<char> >::operator<<+10873"
    },
    {
      "pc": "0x00007ff7c4535b7c",
      "symbol": "std::basic_ostream<char,std::char_traits<char> >::operator<<+28316"
    },
    {
      "pc": "0x00007ff7c4534b38",
      "symbol": "std::basic_ostream<char,std::char_traits<char> >::operator<<+24152"
    },
    {
      "pc": "0x00007ff7c462446b",
      "symbol": "v8::base::CPU::has_sse+37723"
    },
    {
      "pc": "0x00007ff7c4e28d9e",
      "symbol": "v8::Isolate::ReportExternalAllocationLimitReached+94"
    },
    {
      "pc": "0x00007ff7c4e10de1",
      "symbol": "v8::SharedArrayBuffer::Externalize+833"
    },
    {
      "pc": "0x00007ff7c4cde6ac",
      "symbol": "v8::internal::Heap::EphemeronKeyWriteBarrierFromCode+1436"
    },
    {
      "pc": "0x00007ff7c4ce9a50",
      "symbol": "v8::internal::Heap::ProtectUnprotectedMemoryChunks+1312"
    },
    {
      "pc": "0x00007ff7c4ce6584",
      "symbol": "v8::internal::Heap::PageFlagsAreConsistent+3204"
    },
    {
      "pc": "0x00007ff7c4cdbe13",
      "symbol": "v8::internal::Heap::CollectGarbage+1283"
    },
    {
      "pc": "0x00007ff7c4cda5e4",
      "symbol": "v8::internal::Heap::AddRetainedMap+2356"
    },
    {
      "pc": "0x00007ff7c4cfb8b5",
      "symbol": "v8::internal::Factory::NewFillerObject+53"
    },
    {
      "pc": "0x00007ff7c4a67b89",
      "symbol": "v8::internal::interpreter::JumpTableTargetOffsets::iterator::operator=+4057"
    },
    {
      "pc": "0x00007ff7c5254d3d",
      "symbol": "v8::internal::SetupIsolateDelegate::SetupHeap+567949"
    },
    {
      "pc": "0x00007ff7c51d04f4",
      "symbol": "v8::internal::SetupIsolateDelegate::SetupHeap+25156"
    },
    {
      "pc": "0x00007ff7c52bb043",
      "symbol": "v8::internal::SetupIsolateDelegate::SetupHeap+986515"
    },
    {
      "pc": "0x00007ff7c51d48cc",
      "symbol": "v8::internal::SetupIsolateDelegate::SetupHeap+42524"
    },
    {
      "pc": "0x00007ff7c51d48cc",
      "symbol": "v8::internal::SetupIsolateDelegate::SetupHeap+42524"
    },
    {
      "pc": "0x00007ff7c51d48cc",
      "symbol": "v8::internal::SetupIsolateDelegate::SetupHeap+42524"
    },
    {
      "pc": "0x00007ff7c51d48cc",
      "symbol": "v8::internal::SetupIsolateDelegate::SetupHeap+42524"
    },
    {
      "pc": "0x00007ff7c51d48cc",
      "symbol": "v8::internal::SetupIsolateDelegate::SetupHeap+42524"
    },
    {
      "pc": "0x00007ff7c51d48cc",
      "symbol": "v8::internal::SetupIsolateDelegate::SetupHeap+42524"
    },
    {
      "pc": "0x00007ff7c51d48cc",
      "symbol": "v8::internal::SetupIsolateDelegate::SetupHeap+42524"
    },
    {
      "pc": "0x00007ff7c51d48cc",
      "symbol": "v8::internal::SetupIsolateDelegate::SetupHeap+42524"
    },
    {
      "pc": "0x00007ff7c51d48cc",
      "symbol": "v8::internal::SetupIsolateDelegate::SetupHeap+42524"
    },
    {
      "pc": "0x00007ff7c51d48cc",
      "symbol": "v8::internal::SetupIsolateDelegate::SetupHeap+42524"
    },
    {
      "pc": "0x000000b43890e990",
      "symbol": ""
    }
  ],
  "javascriptHeap": {
    "totalMemory": 2171969536,
    "totalCommittedMemory": 2171969536,
    "usedMemory": 2093116504,
    "availableMemory": 56789264,
    "memoryLimit": 2197815296,
    "heapSpaces": {
      "read_only_space": {
        "memorySize": 262144,
        "committedMemory": 262144,
        "capacity": 261872,
        "used": 32296,
        "available": 229576
      },
      "new_space": {
        "memorySize": 33554432,
        "committedMemory": 33554432,
        "capacity": 16759808,
        "used": 2903088,
        "available": 13856720
      },
      "old_space": {
        "memorySize": 1901441024,
        "committedMemory": 1901441024,
        "capacity": 1869665608,
        "used": 1869568208,
        "available": 97400
      },
      "code_space": {
        "memorySize": 8814592,
        "committedMemory": 8814592,
        "capacity": 7476928,
        "used": 7476928,
        "available": 0
      },
      "map_space": {
        "memorySize": 14946304,
        "committedMemory": 14946304,
        "capacity": 1091840,
        "used": 1091840,
        "available": 0
      },
      "large_object_space": {
        "memorySize": 212901888,
        "committedMemory": 212901888,
        "capacity": 212040592,
        "used": 212040592,
        "available": 0
      },
      "code_large_object_space": {
        "memorySize": 49152,
        "committedMemory": 49152,
        "capacity": 3552,
        "used": 3552,
        "available": 0
      },
      "new_large_object_space": {
        "memorySize": 0,
        "committedMemory": 0,
        "capacity": 16759808,
        "used": 0,
        "available": 16759808
      }
    }
  },
  "resourceUsage": {
    "userCpuSeconds": 294.953,
    "kernelCpuSeconds": 19.156,
    "cpuConsumptionPercent": 3.99477,
    "maxRss": 2242936832,
    "pageFaults": {
      "IORequired": 1915240,
      "IONotRequired": 0
    },
    "fsActivity": {
      "reads": 31923,
      "writes": 9
    }
  },
  "libuv": [
  ],
  "environmentVariables": {
    "ALLUSERSPROFILE": "C:\\ProgramData",
    "APPDATA": "C:\\Users\\aclavero\\AppData\\Roaming",
    "BROWSERSLIST_IGNORE_OLD_DATA": "1",
    "CLIENTNAME": "W10",
    "COLORTERM": "truecolor",
    "CommonProgramFiles": "C:\\Program Files\\Common Files",
    "CommonProgramFiles(x86)": "C:\\Program Files (x86)\\Common Files",
    "CommonProgramW6432": "C:\\Program Files\\Common Files",
    "COMPUTERNAME": "WKS143",
    "ComSpec": "C:\\WINDOWS\\system32\\cmd.exe",
    "DriverData": "C:\\Windows\\System32\\Drivers\\DriverData",
    "FILESYSTEMROOT": "C:\\Emerix",
    "GIT_ASKPASS": "c:\\Users\\aclavero\\AppData\\Local\\Programs\\Microsoft VS Code\\resources\\app\\extensions\\git\\dist\\askpass.sh",
    "HOMEDRIVE": "H:",
    "HOMEPATH": "\\",
    "HOMESHARE": "\\\\srv012\\home\\aclavero",
    "LANG": "es_ES.UTF-8",
    "LIBPATH": "C:\\Pentaho\\Data-Integration",
    "LOCALAPPDATA": "C:\\Users\\aclavero\\AppData\\Local",
    "LOGONSERVER": "\\\\SRVDCP01",
    "MSMPI_BENCHMARKS": "C:\\Program Files\\Microsoft MPI\\Benchmarks\\",
    "MSMPI_BIN": "C:\\Program Files\\Microsoft MPI\\Bin\\",
    "NUMBER_OF_PROCESSORS": "12",
    "OneDrive": "C:\\Users\\aclavero\\OneDrive",
    "ORIGINAL_XDG_CURRENT_DESKTOP": "undefined",
    "OS": "Windows_NT",
    "Path": "C:\\Program Files (x86)\\Common Files\\Oracle\\Java\\javapath;C:\\Program Files\\Microsoft MPI\\Bin\\;F:\\oraclexe\\app\\oracle\\product\\11.2.0\\server\\bin;C:\\ProgramData\\Oracle\\Java\\javapath;C:\\WINDOWS\\system32;C:\\WINDOWS;C:\\WINDOWS\\System32\\Wbem;C:\\WINDOWS\\System32\\WindowsPowerShell\\v1.0\\;C:\\WINDOWS\\System32\\OpenSSH\\;C:\\Program Files\\dotnet\\;C:\\Program Files\\Microsoft SQL Server\\130\\Tools\\Binn\\;C:\\Program Files (x86)\\Microsoft SQL Server\\150\\DTS\\Binn\\;C:\\Program Files (x86)\\Microsoft SQL Server\\110\\DTS\\Binn\\;C:\\Program Files (x86)\\Microsoft SQL Server\\120\\DTS\\Binn\\;C:\\Program Files (x86)\\Microsoft SQL Server\\130\\DTS\\Binn\\;C:\\Program Files (x86)\\Microsoft SQL Server\\140\\DTS\\Binn\\;C:\\Program Files (x86)\\Microsoft Visual Studio\\Shared\\Python36_64\\Scripts\\;C:\\Program Files\\nodejs\\;C:\\Program Files (x86)\\Microsoft SQL Server\\150\\Tools\\Binn\\;C:\\Program Files\\Microsoft SQL Server\\150\\Tools\\Binn\\;C:\\Program Files\\Microsoft SQL Server\\150\\DTS\\Binn\\;C:\\Program Files (x86)\\Microsoft SQL Server\\130\\Tools\\Binn\\;C:\\Program Files\\Microsoft SQL Server\\130\\DTS\\Binn\\;C:\\Program Files\\Microsoft SQL Server\\Client SDK\\ODBC\\130\\Tools\\Binn\\;F:\\Program Files\\Git\\cmd;C:\\Program Files\\PuTTY\\;C:\\Program Files\\Microsoft VS Code\\bin;C:\\Users\\aclavero\\AppData\\Local\\Programs\\Python\\Python38-32;C:\\Users\\aclavero\\AppData\\Local\\Microsoft\\WindowsApps;C:\\Users\\aclavero\\AppData\\Roaming\\npm;C:\\Users\\aclavero\\AppData\\Local\\Programs\\Microsoft VS Code\\bin;",
    "PATHEXT": ".COM;.EXE;.BAT;.CMD;.VBS;.VBE;.JS;.JSE;.WSF;.WSH;.MSC;.CPL",
    "PDI_HOME": "C:\\Pentaho\\Data-Integration",
    "PENTAHO_JAVA_HOME": "C:\\Program Files\\Java\\jdk1.8.0_131",
    "PROCESSOR_ARCHITECTURE": "AMD64",
    "PROCESSOR_IDENTIFIER": "Intel64 Family 6 Model 158 Stepping 10, GenuineIntel",
    "PROCESSOR_LEVEL": "6",
    "PROCESSOR_REVISION": "9e0a",
    "ProgramData": "C:\\ProgramData",
    "ProgramFiles": "C:\\Program Files",
    "ProgramFiles(x86)": "C:\\Program Files (x86)",
    "ProgramW6432": "C:\\Program Files",
    "PSModulePath": "C:\\Users\\aclavero\\Documents\\WindowsPowerShell\\Modules;C:\\Program Files\\WindowsPowerShell\\Modules;C:\\WINDOWS\\system32\\WindowsPowerShell\\v1.0\\Modules;C:\\Program Files (x86)\\Microsoft SQL Server\\130\\Tools\\PowerShell\\Modules\\",
    "PUBLIC": "C:\\Users\\Public",
    "SESSIONNAME": "RDP-Tcp#66",
    "SYBASE": "F:\\Program Files (x86)\\Quest Software\\Toad for Data Analysts 3.0\\",
    "SystemDrive": "C:",
    "SystemRoot": "C:\\WINDOWS",
    "TEMP": "C:\\Users\\aclavero\\AppData\\Local\\Temp",
    "TERM_PROGRAM": "vscode",
    "TERM_PROGRAM_VERSION": "1.48.1",
    "TMP": "C:\\Users\\aclavero\\AppData\\Local\\Temp",
    "USERDNSDOMAIN": "SOFTOFFICE.COM.AR",
    "USERDOMAIN": "SOFTOFFICE",
    "USERDOMAIN_ROAMINGPROFILE": "SOFTOFFICE",
    "USERNAME": "aclavero",
    "USERPROFILE": "C:\\Users\\aclavero",
    "VBOX_MSI_INSTALL_PATH": "C:\\Program Files\\Oracle\\VirtualBox\\",
    "VSCODE_GIT_ASKPASS_MAIN": "c:\\Users\\aclavero\\AppData\\Local\\Programs\\Microsoft VS Code\\resources\\app\\extensions\\git\\dist\\askpass-main.js",
    "VSCODE_GIT_ASKPASS_NODE": "C:\\Users\\aclavero\\AppData\\Local\\Programs\\Microsoft VS Code\\Code.exe",
    "VSCODE_GIT_IPC_HANDLE": "\\\\.\\pipe\\vscode-git-659c0720e4-sock",
    "WEBPACK_DEV_SERVER": "true",
    "windir": "C:\\WINDOWS"
  },
  "sharedObjects": [
    "C:\\Program Files\\nodejs\\node.exe",
    "C:\\WINDOWS\\SYSTEM32\\ntdll.dll",
    "C:\\WINDOWS\\System32\\KERNEL32.DLL",
    "C:\\WINDOWS\\System32\\KERNELBASE.dll",
    "C:\\WINDOWS\\System32\\WS2_32.dll",
    "C:\\WINDOWS\\System32\\RPCRT4.dll",
    "C:\\WINDOWS\\SYSTEM32\\dbghelp.dll",
    "C:\\WINDOWS\\System32\\ADVAPI32.dll",
    "C:\\WINDOWS\\System32\\ucrtbase.dll",
    "C:\\WINDOWS\\System32\\msvcrt.dll",
    "C:\\WINDOWS\\System32\\sechost.dll",
    "C:\\WINDOWS\\System32\\USER32.dll",
    "C:\\WINDOWS\\System32\\win32u.dll",
    "C:\\WINDOWS\\System32\\GDI32.dll",
    "C:\\WINDOWS\\System32\\gdi32full.dll",
    "C:\\WINDOWS\\System32\\msvcp_win.dll",
    "C:\\WINDOWS\\System32\\PSAPI.DLL",
    "C:\\WINDOWS\\System32\\CRYPT32.dll",
    "C:\\WINDOWS\\System32\\MSASN1.dll",
    "C:\\WINDOWS\\System32\\bcrypt.dll",
    "C:\\WINDOWS\\SYSTEM32\\USERENV.dll",
    "C:\\WINDOWS\\SYSTEM32\\IPHLPAPI.DLL",
    "C:\\WINDOWS\\System32\\profapi.dll",
    "C:\\WINDOWS\\SYSTEM32\\WINMM.dll",
    "C:\\WINDOWS\\SYSTEM32\\WINMMBASE.dll",
    "C:\\WINDOWS\\System32\\cfgmgr32.dll",
    "C:\\WINDOWS\\System32\\bcryptPrimitives.dll",
    "C:\\WINDOWS\\System32\\IMM32.DLL",
    "C:\\WINDOWS\\System32\\powrprof.dll",
    "C:\\WINDOWS\\System32\\UMPDC.dll",
    "C:\\WINDOWS\\SYSTEM32\\CRYPTBASE.DLL",
    "C:\\WINDOWS\\system32\\uxtheme.dll",
    "C:\\WINDOWS\\System32\\combase.dll",
    "C:\\WINDOWS\\system32\\mswsock.dll",
    "C:\\WINDOWS\\System32\\kernel.appcore.dll",
    "C:\\WINDOWS\\System32\\NSI.dll",
    "C:\\WINDOWS\\SYSTEM32\\dhcpcsvc6.DLL",
    "C:\\WINDOWS\\SYSTEM32\\dhcpcsvc.DLL",
    "C:\\WINDOWS\\SYSTEM32\\DNSAPI.dll",
    "C:\\WINDOWS\\system32\\napinsp.dll",
    "C:\\WINDOWS\\system32\\pnrpnsp.dll",
    "C:\\WINDOWS\\System32\\winrnr.dll",
    "C:\\WINDOWS\\system32\\NLAapi.dll",
    "C:\\WINDOWS\\system32\\wshbth.dll"
  ]
}